MANIFEST.in
README.rst
setup.cfg
setup.py
django_social_links/__init__.py
django_social_links/admin.py
django_social_links/models.py
django_social_links.egg-info/PKG-INFO
django_social_links.egg-info/SOURCES.txt
django_social_links.egg-info/dependency_links.txt
django_social_links.egg-info/top_level.txt
django_social_links/migrations/0001_initial.py
django_social_links/migrations/__init__.py
django_social_links/templatetags/__init__.py
django_social_links/templatetags/django_social.py