Metadata-Version: 1.0
Name: django-social-links
Version: 0.0.1
Summary: Django social links module
Home-page: UNKNOWN
Author: Spi4ka
Author-email: UNKNOWN
License: UNKNOWN
Platform: UNKNOWN
